{
  "type": "light",
  "colors": {
    "contrastActiveBorder": "#00308700",
    "contrastBorder": "#00308700",
    "editor.background": "#FFFFFF",
    "editor.foreground": "#0A0C18",
    "editorCursor.foreground": "#003087",
    "editorCursor.background": "#FFFFFF",
    "editor.lineHighlightBackground": "#F5F5F5",
    "editor.lineHighlightBorder": "#00308710",
    "editor.inactiveLineHighlightBackground": "#F5F5F580",
    "editor.selectionBackground": "#00308730",
    "editor.selectionForeground": "#0A0C18",
    "editor.inactiveSelectionBackground": "#00308720",
    "editor.selectionHighlightBackground": "#00308720",
    "editor.selectionHighlightBorder": "#00308740",
    "editor.findMatchBackground": "#00308750",
    "editor.findMatchForeground": "#0A0C18",
    "editor.findMatchHighlightBackground": "#00308730",
    "editor.findMatchHighlightForeground": "#0A0C18",
    "editor.findRangeHighlightBackground": "#00308715",
    "editor.findMatchBorder": "#003087",
    "editor.findMatchHighlightBorder": "#00308760",
    "editor.findRangeHighlightBorder": "#00308700",
    "editor.hoverHighlightBackground": "#00308715",
    "editor.wordHighlightBackground": "#00308720",
    "editor.wordHighlightBorder": "#00308740",
    "editor.wordHighlightStrongBackground": "#00308730",
    "editor.wordHighlightStrongBorder": "#00308760",
    "editor.wordHighlightTextBackground": "#00308715",
    "editor.wordHighlightTextBorder": "#00308730",
    "editor.rangeHighlightBackground": "#00308710",
    "editor.rangeHighlightBorder": "#00308700",
    "editor.symbolHighlightBackground": "#00308720",
    "editor.symbolHighlightBorder": "#00308740",
    "editor.linkedEditingBackground": "#00308720",
    "editor.foldBackground": "#00308710",
    "editor.foldPlaceholderForeground": "#78797E",
    "editor.placeholder.foreground": "#78797E",
    "editor.compositionBorder": "#003087",
    "editorSnippetTabstopHighlightBackground": "#00308720",
    "editorSnippetTabstopHighlightBorder": "#00308700",
    "editorSnippetFinalTabstopHighlightBackground": "#339D3720",
    "editorSnippetFinalTabstopHighlightBorder": "#339D3700",
    "editor.stackFrameHighlightBackground": "#B3880020",
    "editor.focusedStackFrameHighlightBackground": "#339D3720",
    "editor.inlineValuesForeground": "#78797E",
    "editor.inlineValuesBackground": "#00308710",
    "editorLineNumber.foreground": "#7A6500",
    "editorLineNumber.activeForeground": "#003087",
    "editorLineNumber.dimmedForeground": "#78797E50",
    "editorMultiCursor.primary.foreground": "#003087",
    "editorMultiCursor.primary.background": "#FFFFFF",
    "editorMultiCursor.secondary.foreground": "#7A6500",
    "editorMultiCursor.secondary.background": "#FFFFFF",
    "editorIndentGuide.background1": "#00308720",
    "editorIndentGuide.background2": "#7A650020",
    "editorIndentGuide.background3": "#B3880020",
    "editorIndentGuide.background4": "#0A690D20",
    "editorIndentGuide.background5": "#5B9BD520",
    "editorIndentGuide.background6": "#006A8F20",
    "editorIndentGuide.activeBackground1": "#003087",
    "editorIndentGuide.activeBackground2": "#7A6500",
    "editorIndentGuide.activeBackground3": "#B38800",
    "editorIndentGuide.activeBackground4": "#0A690D",
    "editorIndentGuide.activeBackground5": "#5B9BD5",
    "editorIndentGuide.activeBackground6": "#006A8F",
    "editorWhitespace.foreground": "#7A650050",
    "editorRuler.foreground": "#E0E0E030",
    "editorUnicodeHighlight.border": "#B38800",
    "editorUnicodeHighlight.background": "#B3880015",
    "editorLink.activeForeground": "#003087",
    "editorCodeLens.foreground": "#78797E",
    "editorLightBulb.foreground": "#B38800",
    "editorLightBulbAutoFix.foreground": "#339D37",
    "editorLightBulbAi.foreground": "#003087",
    "editorBracketMatch.border": "#00308760",
    "editorBracketHighlight.foreground1": "#003087",
    "editorBracketHighlight.foreground2": "#7A6500",
    "editorBracketHighlight.foreground3": "#B38800",
    "editorBracketHighlight.foreground4": "#0A690D",
    "editorBracketHighlight.foreground5": "#5B9BD5",
    "editorBracketHighlight.foreground6": "#006A8F",
    "editorBracketHighlight.unexpectedBracket.foreground": "#E22339",
    "editorBracketPairGuide.activeBackground1": "#00308780",
    "editorBracketPairGuide.activeBackground2": "#7A650080",
    "editorBracketPairGuide.activeBackground3": "#B3880080",
    "editorBracketPairGuide.activeBackground4": "#0A690D80",
    "editorBracketPairGuide.activeBackground5": "#5B9BD580",
    "editorBracketPairGuide.activeBackground6": "#006A8F80",
    "editorBracketPairGuide.background1": "#00308740",
    "editorBracketPairGuide.background2": "#7A650040",
    "editorBracketPairGuide.background3": "#B3880040",
    "editorBracketPairGuide.background4": "#0A690D40",
    "editorBracketPairGuide.background5": "#5B9BD540",
    "editorBracketPairGuide.background6": "#006A8F40",
    "editorError.foreground": "#E22339",
    "editorError.border": "#E2233900",
    "editorError.background": "#E2233910",
    "editorWarning.foreground": "#B38800",
    "editorWarning.border": "#B3880000",
    "editorWarning.background": "#B3880010",
    "editorInfo.foreground": "#5B9BD5",
    "editorInfo.border": "#5B9BD500",
    "editorInfo.background": "#5B9BD510",
    "editorHint.foreground": "#339D37",
    "editorHint.border": "#339D3700",
    "problemsErrorIcon.foreground": "#E22339",
    "problemsWarningIcon.foreground": "#B38800",
    "problemsInfoIcon.foreground": "#5B9BD5",
    "editorUnnecessaryCode.border": "#78797E40",
    "editorUnnecessaryCode.opacity": "#00000077",
    "editorGutter.background": "#FFFFFF",
    "editorGutter.modifiedBackground": "#003087",
    "editorGutter.addedBackground": "#339D37",
    "editorGutter.deletedBackground": "#E22339",
    "editorGutter.commentRangeForeground": "#78797E40",
    "editorGutter.commentGlyphForeground": "#003087",
    "editorGutter.commentUnresolvedGlyphForeground": "#B38800",
    "editorGutter.modifiedSecondaryBackground": "#00308760",
    "editorGutter.addedSecondaryBackground": "#339D3760",
    "editorGutter.deletedSecondaryBackground": "#E2233960",
    "editorGutter.foldingControlForeground": "#78797E",
    "editorGutter.itemBackground": "#FFFFFF",
    "editorGutter.itemGlyphForeground": "#003087",
    "editorGutter.commentDraftGlyphForeground": "#00308780",
    "editorStickyScroll.background": "#F5F5F5",
    "editorStickyScroll.border": "#7A650015",
    "editorStickyScroll.shadow": "#0A0C1815",
    "editorStickyScrollHover.background": "#E0E0E0",
    "editorCommentsWidget.resolvedBorder": "#339D3750",
    "editorCommentsWidget.unresolvedBorder": "#B38800",
    "editorCommentsWidget.rangeBackground": "#00308708",
    "editorCommentsWidget.rangeActiveBackground": "#00308715",
    "editorCommentsWidget.replyInputBackground": "#FFFFFF",
    "inlineEdit.modifiedBackground": "#00308710",
    "inlineEdit.modifiedChangedLineBackground": "#00308715",
    "inlineEdit.modifiedChangedTextBackground": "#00308725",
    "inlineEdit.originalBackground": "#E2233908",
    "inlineEdit.originalChangedLineBackground": "#E2233910",
    "inlineEdit.originalChangedTextBackground": "#E2233920",
    "inlineEdit.modifiedBorder": "#00308740",
    "inlineEdit.originalBorder": "#E2233925",
    "inlineEdit.tabWillAcceptModifiedBorder": "#339D3760",
    "inlineEdit.tabWillAcceptOriginalBorder": "#E2233940",
    "inlineEdit.gutterIndicator.background": "#FFFFFF",
    "inlineEdit.gutterIndicator.primaryBorder": "#003087",
    "inlineEdit.gutterIndicator.primaryForeground": "#003087",
    "inlineEdit.gutterIndicator.primaryBackground": "#00308715",
    "inlineEdit.gutterIndicator.secondaryBorder": "#7A6500",
    "inlineEdit.gutterIndicator.secondaryForeground": "#7A6500",
    "inlineEdit.gutterIndicator.secondaryBackground": "#7A650015",
    "inlineEdit.gutterIndicator.successfulBorder": "#339D37",
    "inlineEdit.gutterIndicator.successfulForeground": "#339D37",
    "inlineEdit.gutterIndicator.successfulBackground": "#339D3715",
    "search.resultsInfoForeground": "#78797E",
    "searchEditor.findMatchBackground": "#00308730",
    "searchEditor.findMatchBorder": "#00308760",
    "searchEditor.textInputBorder": "#00308750",
    "activityBar.background": "#F5F5F5",
    "activityBar.foreground": "#0A0C18",
    "activityBar.inactiveForeground": "#44444470",
    "activityBar.border": "#7A650030",
    "activityBar.activeBorder": "#7A6500",
    "activityBar.activeBackground": "#7A650015",
    "activityBar.activeFocusBorder": "#7A6500",
    "activityBar.dropBorder": "#7A6500",
    "activityBarBadge.background": "#003087",
    "activityBarBadge.foreground": "#FFFFFF",
    "activityBarTop.foreground": "#0A0C18",
    "activityBarTop.activeBorder": "#7A6500",
    "activityBarTop.inactiveForeground": "#44444470",
    "activityBarTop.dropBorder": "#7A6500",
    "activityBarTop.background": "#F5F5F5",
    "activityBarTop.activeBackground": "#7A650015",
    "activityWarningBadge.foreground": "#FFFFFF",
    "activityWarningBadge.background": "#B38800",
    "activityErrorBadge.foreground": "#FFFFFF",
    "activityErrorBadge.background": "#E22339",
    "profileBadge.background": "#003087",
    "profileBadge.foreground": "#FFFFFF",
    "profiles.sashBorder": "#003087",
    "sideBar.background": "#F5F5F5",
    "sideBar.foreground": "#0A0C18",
    "sideBar.border": "#7A650030",
    "sideBar.dropBackground": "#00308720",
    "sideBarTitle.foreground": "#7A6500",
    "sideBarTitle.background": "#F5F5F5",
    "sideBarTitle.border": "#7A650015",
    "sideBarSectionHeader.background": "#7A650015",
    "sideBarSectionHeader.foreground": "#00206B",
    "sideBarSectionHeader.border": "#7A650020",
    "sideBarActivityBarTop.border": "#7A650020",
    "sideBarStickyScroll.background": "#F5F5F5",
    "sideBarStickyScroll.border": "#7A650015",
    "sideBarStickyScroll.shadow": "#0A0C1815",
    "list.activeSelectionBackground": "#00308740",
    "list.activeSelectionForeground": "#FFFFFF",
    "list.activeSelectionIconForeground": "#FFFFFF",
    "list.inactiveSelectionBackground": "#00308720",
    "list.inactiveSelectionForeground": "#0A0C18",
    "list.inactiveSelectionIconForeground": "#0A0C18",
    "list.inactiveFocusBackground": "#00308715",
    "list.hoverBackground": "#00308715",
    "list.hoverForeground": "#0A0C18",
    "list.focusBackground": "#00308730",
    "list.focusForeground": "#0A0C18",
    "list.focusHighlightForeground": "#003087",
    "list.focusOutline": "#00308760",
    "list.focusAndSelectionOutline": "#003087",
    "list.highlightForeground": "#003087",
    "list.dropBackground": "#00308720",
    "list.dropBetweenBackground": "#003087",
    "list.invalidItemForeground": "#E22339",
    "list.errorForeground": "#E22339",
    "list.warningForeground": "#B38800",
    "list.deemphasizedForeground": "#78797E",
    "list.inactiveFocusOutline": "#00308740",
    "list.filterMatchBorder": "#00308760",
    "listFilterWidget.background": "#FFFFFF",
    "listFilterWidget.outline": "#003087",
    "listFilterWidget.noMatchesOutline": "#E22339",
    "listFilterWidget.shadow": "#0A0C1830",
    "tree.indentGuidesStroke": "#7A650030",
    "tree.inactiveIndentGuidesStroke": "#7A650015",
    "tree.tableColumnsBorder": "#7A650015",
    "tree.tableOddRowsBackground": "#F5F5F580",
    "titleBar.activeBackground": "#F5F5F5",
    "titleBar.activeForeground": "#0A0C18",
    "titleBar.inactiveBackground": "#F5F5F5",
    "titleBar.inactiveForeground": "#44444470",
    "titleBar.border": "#7A650030",
    "commandCenter.foreground": "#0A0C18",
    "commandCenter.activeForeground": "#0A0C18",
    "commandCenter.background": "#0A0C1815",
    "commandCenter.activeBackground": "#0A0C1825",
    "commandCenter.border": "#0A0C1830",
    "commandCenter.inactiveForeground": "#44444470",
    "commandCenter.inactiveBorder": "#0A0C1815",
    "commandCenter.activeBorder": "#0A0C1850",
    "commandCenter.debuggingBackground": "#339D3720",
    "statusBar.background": "#003087",
    "statusBar.foreground": "#FFFFFF",
    "statusBar.border": "#00206B",
    "statusBar.noFolderBackground": "#00206B",
    "statusBar.noFolderForeground": "#FFFFFF",
    "statusBar.noFolderBorder": "#00206B",
    "statusBar.debuggingBackground": "#339D37",
    "statusBar.debuggingForeground": "#FFFFFF",
    "statusBar.debuggingBorder": "#339D37CC",
    "statusBar.focusBorder": "#003087",
    "statusBarItem.activeBackground": "#00206B80",
    "statusBarItem.hoverForeground": "#FFFFFF",
    "statusBarItem.hoverBackground": "#00206B80",
    "statusBarItem.prominentForeground": "#FFFFFF",
    "statusBarItem.prominentBackground": "#003087",
    "statusBarItem.prominentHoverForeground": "#FFFFFF",
    "statusBarItem.prominentHoverBackground": "#00206B",
    "statusBarItem.remoteBackground": "#003087",
    "statusBarItem.remoteForeground": "#FFFFFF",
    "statusBarItem.remoteHoverBackground": "#003087CC",
    "statusBarItem.remoteHoverForeground": "#FFFFFF",
    "statusBarItem.errorBackground": "#E22339",
    "statusBarItem.errorForeground": "#FFFFFF",
    "statusBarItem.errorHoverBackground": "#E22339CC",
    "statusBarItem.errorHoverForeground": "#FFFFFF",
    "statusBarItem.warningBackground": "#B38800",
    "statusBarItem.warningForeground": "#FFFFFF",
    "statusBarItem.warningHoverBackground": "#B38800CC",
    "statusBarItem.warningHoverForeground": "#FFFFFF",
    "statusBarItem.compactHoverBackground": "#00206B60",
    "statusBarItem.focusBorder": "#003087",
    "statusBarItem.offlineBackground": "#78797E",
    "statusBarItem.offlineForeground": "#FFFFFF",
    "statusBarItem.offlineHoverForeground": "#FFFFFF",
    "statusBarItem.offlineHoverBackground": "#78797ECC",
    "tab.activeBackground": "#FFFFFF",
    "tab.activeForeground": "#0A0C18",
    "tab.activeBorder": "#7A6500",
    "tab.activeBorderTop": "#7A650000",
    "tab.selectedBorderTop": "#7A6500",
    "tab.selectedBackground": "#FFFFFF",
    "tab.selectedForeground": "#0A0C18",
    "tab.inactiveBackground": "#F5F5F5",
    "tab.inactiveForeground": "#44444470",
    "tab.border": "#7A650020",
    "tab.hoverBackground": "#F5F5F5",
    "tab.hoverForeground": "#0A0C18",
    "tab.hoverBorder": "#7A650040",
    "tab.unfocusedActiveBackground": "#FFFFFF",
    "tab.unfocusedActiveForeground": "#0A0C18CC",
    "tab.unfocusedActiveBorder": "#7A650060",
    "tab.unfocusedActiveBorderTop": "#7A650000",
    "tab.unfocusedInactiveBackground": "#F5F5F5",
    "tab.unfocusedInactiveForeground": "#44444450",
    "tab.unfocusedHoverBackground": "#F5F5F5",
    "tab.unfocusedHoverForeground": "#0A0C18CC",
    "tab.unfocusedHoverBorder": "#7A650030",
    "tab.lastPinnedBorder": "#7A650030",
    "tab.activeModifiedBorder": "#003087",
    "tab.inactiveModifiedBorder": "#00308760",
    "tab.unfocusedActiveModifiedBorder": "#003087CC",
    "tab.unfocusedInactiveModifiedBorder": "#00308750",
    "tab.dragAndDropBorder": "#7A6500",
    "editorGroupHeader.tabsBackground": "#F5F5F5",
    "editorGroupHeader.tabsBorder": "#7A650020",
    "editorGroupHeader.noTabsBackground": "#FFFFFF",
    "editorGroupHeader.border": "#7A650015",
    "editorGroup.border": "#7A650020",
    "editorGroup.dropBackground": "#00308720",
    "editorGroup.emptyBackground": "#FFFFFF",
    "editorGroup.focusedEmptyBorder": "#00308740",
    "editorGroup.dropIntoPromptForeground": "#0A0C18",
    "editorGroup.dropIntoPromptBackground": "#FFFFFF",
    "editorGroup.dropIntoPromptBorder": "#00308750",
    "editorPane.background": "#FFFFFF",
    "sideBySideEditor.horizontalBorder": "#7A650020",
    "sideBySideEditor.verticalBorder": "#7A650020",
    "panel.background": "#F5F5F5",
    "panel.border": "#7A650020",
    "panel.dropBorder": "#7A6500",
    "panelTitle.activeForeground": "#7A6500",
    "panelTitle.inactiveForeground": "#44444460",
    "panelTitle.activeBorder": "#7A6500",
    "panelTitle.border": "#7A650015",
    "panelInput.border": "#00308750",
    "panelSection.border": "#7A650020",
    "panelSection.dropBackground": "#00308720",
    "panelSectionHeader.background": "#7A650015",
    "panelSectionHeader.foreground": "#00206B",
    "panelSectionHeader.border": "#7A650020",
    "panelStickyScroll.background": "#F5F5F5",
    "panelStickyScroll.border": "#7A650015",
    "panelStickyScroll.shadow": "#0A0C1815",
    "panelTitleBadge.background": "#003087",
    "panelTitleBadge.foreground": "#FFFFFF",
    "outputView.background": "#F5F5F5",
    "outputViewStickyScroll.background": "#F5F5F5",
    "terminal.background": "#FFFFFF",
    "terminal.foreground": "#0A0C18",
    "terminal.border": "#7A650020",
    "terminal.ansiBlack": "#0A0C18",
    "terminal.ansiRed": "#E22339",
    "terminal.ansiGreen": "#0A690D",
    "terminal.ansiYellow": "#B38800",
    "terminal.ansiBlue": "#003087",
    "terminal.ansiMagenta": "#5A3D80",
    "terminal.ansiCyan": "#006A8F",
    "terminal.ansiWhite": "#FFFFFF",
    "terminal.ansiBrightBlack": "#78797E",
    "terminal.ansiBrightRed": "#8A1220",
    "terminal.ansiBrightGreen": "#339D37",
    "terminal.ansiBrightYellow": "#FFCD00",
    "terminal.ansiBrightBlue": "#00206B",
    "terminal.ansiBrightMagenta": "#3D2860",
    "terminal.ansiBrightCyan": "#5B9BD5",
    "terminal.ansiBrightWhite": "#FFFFFF",
    "terminal.selectionBackground": "#00308740",
    "terminal.selectionForeground": "#0A0C18",
    "terminal.inactiveSelectionBackground": "#00308720",
    "terminal.findMatchBackground": "#00308760",
    "terminal.findMatchBorder": "#003087",
    "terminal.findMatchHighlightBackground": "#00308740",
    "terminal.findMatchHighlightBorder": "#00308780",
    "terminal.hoverHighlightBackground": "#00308720",
    "terminal.dropBackground": "#00308720",
    "terminal.tab.activeBorder": "#7A6500",
    "terminal.initialHintForeground": "#78797E",
    "terminalCursor.foreground": "#003087",
    "terminalCursor.background": "#FFFFFF",
    "terminalCommandDecoration.defaultBackground": "#00308740",
    "terminalCommandDecoration.successBackground": "#339D3760",
    "terminalCommandDecoration.errorBackground": "#E2233960",
    "terminalOverviewRuler.cursorForeground": "#003087",
    "terminalOverviewRuler.findMatchForeground": "#003087CC",
    "terminalOverviewRuler.border": "#7A650020",
    "terminalStickyScroll.background": "#F5F5F5",
    "terminalStickyScroll.border": "#7A650015",
    "terminalStickyScrollHover.background": "#E0E0E0",
    "terminalCommandGuide.foreground": "#00308720",
    "terminalSymbolIcon.aliasForeground": "#003087",
    "terminalSymbolIcon.branchForeground": "#339D37",
    "terminalSymbolIcon.commitForeground": "#003087",
    "terminalSymbolIcon.flagForeground": "#B38800",
    "terminalSymbolIcon.optionForeground": "#0A0C18",
    "terminalSymbolIcon.optionValueForeground": "#0A690D",
    "terminalSymbolIcon.methodForeground": "#003087",
    "terminalSymbolIcon.argumentForeground": "#006A8F",
    "terminalSymbolIcon.inlineSuggestionForeground": "#78797E",
    "terminalSymbolIcon.fileForeground": "#78797E",
    "terminalSymbolIcon.folderForeground": "#003087",
    "terminalSymbolIcon.pullRequestDoneForeground": "#339D37",
    "terminalSymbolIcon.pullRequestForeground": "#003087",
    "terminalSymbolIcon.remoteForeground": "#7A6500",
    "terminalSymbolIcon.stashForeground": "#003087",
    "terminalSymbolIcon.symbolText": "#0A0C18",
    "terminalSymbolIcon.symbolicLinkFileForeground": "#00308780",
    "terminalSymbolIcon.symbolicLinkFolderForeground": "#00308780",
    "terminalSymbolIcon.tagForeground": "#7A6500",
    "button.background": "#003087",
    "button.foreground": "#FFFFFF",
    "button.border": "#00308700",
    "button.separator": "#FFFFFF40",
    "button.hoverBackground": "#00206B",
    "button.secondaryForeground": "#0A0C18",
    "button.secondaryBackground": "#EBEBEB",
    "button.secondaryHoverBackground": "#E0E0E0",
    "button.secondaryBorder": "#00308740",
    "checkbox.background": "#FFFFFF",
    "checkbox.foreground": "#003087",
    "checkbox.border": "#00308750",
    "checkbox.selectBackground": "#FFFFFF",
    "checkbox.selectBorder": "#003087",
    "checkbox.disabled.background": "#F5F5F5",
    "checkbox.disabled.foreground": "#78797E",
    "radio.activeForeground": "#FFFFFF",
    "radio.activeBackground": "#003087",
    "radio.activeBorder": "#003087",
    "radio.inactiveForeground": "#0A0C18",
    "radio.inactiveBackground": "#FFFFFF",
    "radio.inactiveBorder": "#00308740",
    "radio.inactiveHoverBackground": "#E0E0E0",
    "input.background": "#FFFFFF",
    "input.foreground": "#0A0C18",
    "input.border": "#00308750",
    "input.placeholderForeground": "#78797E",
    "inputOption.activeBackground": "#00308730",
    "inputOption.activeBorder": "#003087",
    "inputOption.activeForeground": "#0A0C18",
    "inputOption.hoverBackground": "#00308715",
    "inputValidation.errorBackground": "#E2233915",
    "inputValidation.errorForeground": "#E22339",
    "inputValidation.errorBorder": "#E22339",
    "inputValidation.infoBackground": "#5B9BD515",
    "inputValidation.infoForeground": "#5B9BD5",
    "inputValidation.infoBorder": "#5B9BD5",
    "inputValidation.warningBackground": "#B3880015",
    "inputValidation.warningForeground": "#B38800",
    "inputValidation.warningBorder": "#B38800",
    "dropdown.background": "#FFFFFF",
    "dropdown.foreground": "#0A0C18",
    "dropdown.border": "#00308750",
    "dropdown.listBackground": "#FFFFFF",
    "scrollbar.background": "#FFFFFF00",
    "scrollbar.shadow": "#0A0C1850",
    "scrollbarSlider.background": "#00308730",
    "scrollbarSlider.hoverBackground": "#00308750",
    "scrollbarSlider.activeBackground": "#00308770",
    "focusBorder": "#003087",
    "foreground": "#0A0C18",
    "disabledForeground": "#78797E",
    "widget.border": "#00308720",
    "widget.shadow": "#0A0C1830",
    "selection.background": "#00308750",
    "descriptionForeground": "#78797E",
    "errorForeground": "#E22339",
    "icon.foreground": "#003087",
    "sash.hoverBorder": "#003087",
    "window.activeBorder": "#00308700",
    "window.inactiveBorder": "#00308700",
    "textBlockQuote.background": "#F5F5F5",
    "textBlockQuote.border": "#00308760",
    "textCodeBlock.background": "#F5F5F5",
    "textLink.activeForeground": "#003087",
    "textLink.foreground": "#003087",
    "textPreformat.foreground": "#0A690D",
    "textPreformat.background": "#F5F5F5",
    "textPreformat.border": "#00308720",
    "textSeparator.foreground": "#00308720",
    "toolbar.hoverBackground": "#00308720",
    "toolbar.hoverOutline": "#00308700",
    "toolbar.activeBackground": "#00308730",
    "editorActionList.background": "#FFFFFF",
    "editorActionList.foreground": "#0A0C18",
    "editorActionList.focusForeground": "#0A0C18",
    "editorActionList.focusBackground": "#00308730",
    "badge.background": "#003087",
    "badge.foreground": "#FFFFFF",
    "progressBar.background": "#003087",
    "menu.background": "#FFFFFF",
    "menu.foreground": "#0A0C18",
    "menu.selectionBackground": "#00308730",
    "menu.selectionForeground": "#0A0C18",
    "menu.selectionBorder": "#00308700",
    "menu.separatorBackground": "#00308720",
    "menu.border": "#00308730",
    "menubar.selectionBackground": "#00308730",
    "menubar.selectionForeground": "#0A0C18",
    "menubar.selectionBorder": "#00308700",
    "notificationCenter.border": "#00308720",
    "notificationCenterHeader.foreground": "#0A0C18",
    "notificationCenterHeader.background": "#F5F5F5",
    "notificationToast.border": "#00308720",
    "notifications.background": "#FFFFFF",
    "notifications.border": "#00308720",
    "notifications.foreground": "#0A0C18",
    "notificationLink.foreground": "#003087",
    "notificationsErrorIcon.foreground": "#E22339",
    "notificationsWarningIcon.foreground": "#B38800",
    "notificationsInfoIcon.foreground": "#5B9BD5",
    "banner.background": "#003087",
    "banner.foreground": "#FFFFFF",
    "banner.iconForeground": "#FFFFFF",
    "editorWidget.foreground": "#0A0C18",
    "editorWidget.background": "#FFFFFF",
    "editorWidget.border": "#00308750",
    "editorWidget.resizeBorder": "#003087",
    "editorSuggestWidget.background": "#FFFFFF",
    "editorSuggestWidget.border": "#00308750",
    "editorSuggestWidget.foreground": "#0A0C18",
    "editorSuggestWidget.focusHighlightForeground": "#003087",
    "editorSuggestWidget.highlightForeground": "#003087",
    "editorSuggestWidget.selectedBackground": "#00308750",
    "editorSuggestWidget.selectedForeground": "#0A0C18",
    "editorSuggestWidget.selectedIconForeground": "#0A0C18",
    "editorSuggestWidgetStatus.foreground": "#78797E",
    "editorHoverWidget.foreground": "#0A0C18",
    "editorHoverWidget.background": "#FFFFFF",
    "editorHoverWidget.border": "#00308750",
    "editorHoverWidget.highlightForeground": "#003087",
    "editorHoverWidget.statusBarBackground": "#F5F5F5",
    "editorGhostText.foreground": "#0A0C1866",
    "editorGhostText.background": "#00308700",
    "editorGhostText.border": "#00308700",
    "editorStickyScrollGutter.background": "#F5F5F5",
    "debugExceptionWidget.background": "#E2233915",
    "debugExceptionWidget.border": "#E2233960",
    "editorMarkerNavigation.background": "#FFFFFF",
    "editorMarkerNavigationError.background": "#E2233920",
    "editorMarkerNavigationWarning.background": "#B3880020",
    "editorMarkerNavigationInfo.background": "#5B9BD520",
    "editorMarkerNavigationError.headerBackground": "#E2233915",
    "editorMarkerNavigationWarning.headerBackground": "#B3880015",
    "editorMarkerNavigationInfo.headerBackground": "#5B9BD515",
    "peekView.border": "#003087",
    "peekViewEditor.background": "#161928",
    "peekViewEditorGutter.background": "#161928",
    "peekViewEditor.matchHighlightBackground": "#00308750",
    "peekViewEditor.matchHighlightBorder": "#00308780",
    "peekViewResult.background": "#0A0C18",
    "peekViewResult.fileForeground": "#FFFFFF",
    "peekViewResult.lineForeground": "#A8B8D0",
    "peekViewResult.matchHighlightBackground": "#00308750",
    "peekViewResult.selectionBackground": "#00308750",
    "peekViewResult.selectionForeground": "#FFFFFF",
    "peekViewTitle.background": "#050710",
    "peekViewTitleDescription.foreground": "#A8B8D0",
    "peekViewTitleLabel.foreground": "#003087",
    "peekViewEditorStickyScroll.background": "#161928",
    "peekViewEditorStickyScrollGutter.background": "#161928",
    "merge.currentHeaderBackground": "#339D3750",
    "merge.currentContentBackground": "#339D3720",
    "merge.incomingHeaderBackground": "#00308750",
    "merge.incomingContentBackground": "#00308720",
    "merge.commonHeaderBackground": "#78797E30",
    "merge.commonContentBackground": "#78797E15",
    "merge.border": "#00308750",
    "mergeEditor.change.background": "#00308715",
    "mergeEditor.change.word.background": "#00308730",
    "mergeEditor.conflict.unhandledUnfocused.border": "#B3880060",
    "mergeEditor.conflict.unhandledFocused.border": "#B38800",
    "mergeEditor.conflict.handledUnfocused.border": "#339D3740",
    "mergeEditor.conflict.handledFocused.border": "#339D37",
    "mergeEditor.conflict.handled.minimapOverViewRuler": "#339D37",
    "mergeEditor.conflict.unhandled.minimapOverViewRuler": "#B38800",
    "mergeEditor.conflictingLines.background": "#B3880015",
    "mergeEditor.changeBase.background": "#78797E10",
    "mergeEditor.changeBase.word.background": "#78797E20",
    "mergeEditor.conflict.input1.background": "#339D3715",
    "mergeEditor.conflict.input2.background": "#00308715",
    "editorOverviewRuler.background": "#FFFFFF",
    "editorOverviewRuler.border": "#00308720",
    "editorOverviewRuler.findMatchForeground": "#003087CC",
    "editorOverviewRuler.rangeHighlightForeground": "#00308799",
    "editorOverviewRuler.selectionHighlightForeground": "#00308799",
    "editorOverviewRuler.wordHighlightForeground": "#00308799",
    "editorOverviewRuler.wordHighlightStrongForeground": "#003087CC",
    "editorOverviewRuler.wordHighlightTextForeground": "#00308760",
    "editorOverviewRuler.modifiedForeground": "#003087",
    "editorOverviewRuler.addedForeground": "#339D37",
    "editorOverviewRuler.deletedForeground": "#E22339",
    "editorOverviewRuler.errorForeground": "#E22339",
    "editorOverviewRuler.warningForeground": "#B38800",
    "editorOverviewRuler.infoForeground": "#5B9BD5",
    "editorOverviewRuler.bracketMatchForeground": "#00308760",
    "editorOverviewRuler.currentContentForeground": "#339D3760",
    "editorOverviewRuler.incomingContentForeground": "#00308760",
    "editorOverviewRuler.commonContentForeground": "#78797E40",
    "editorOverviewRuler.commentForeground": "#00308730",
    "editorOverviewRuler.commentUnresolvedForeground": "#B3880060",
    "editorOverviewRuler.commentDraftForeground": "#00308750",
    "editorOverviewRuler.inlineChatInserted": "#339D3760",
    "editorOverviewRuler.inlineChatRemoved": "#E2233960",
    "minimap.findMatchHighlight": "#00308780",
    "minimap.selectionHighlight": "#00308750",
    "minimap.errorHighlight": "#E22339",
    "minimap.warningHighlight": "#B38800",
    "minimap.background": "#FFFFFF",
    "minimap.selectionOccurrenceHighlight": "#00308730",
    "minimap.foregroundOpacity": "#000000FF",
    "minimap.infoHighlight": "#5B9BD5",
    "minimap.chatEditHighlight": "#00308730",
    "editorMinimap.inlineChatInserted": "#339D3730",
    "minimapSlider.background": "#00308730",
    "minimapSlider.hoverBackground": "#00308750",
    "minimapSlider.activeBackground": "#00308770",
    "minimapGutter.addedBackground": "#339D37",
    "minimapGutter.modifiedBackground": "#003087",
    "minimapGutter.deletedBackground": "#E22339",
    "diffEditor.insertedTextBackground": "#339D3720",
    "diffEditor.removedTextBackground": "#E2233920",
    "diffEditor.insertedTextBorder": "#339D3750",
    "diffEditor.removedTextBorder": "#E2233950",
    "diffEditor.border": "#7A650020",
    "diffEditor.diagonalFill": "#78797E15",
    "diffEditor.insertedLineBackground": "#339D3710",
    "diffEditor.removedLineBackground": "#E2233910",
    "diffEditorGutter.insertedLineBackground": "#339D3720",
    "diffEditorGutter.removedLineBackground": "#E2233920",
    "diffEditorOverview.insertedForeground": "#339D3760",
    "diffEditorOverview.removedForeground": "#E2233960",
    "diffEditor.unchangedRegionBackground": "#F5F5F5",
    "diffEditor.unchangedRegionForeground": "#78797E",
    "diffEditor.unchangedRegionShadow": "#0A0C1815",
    "diffEditor.unchangedCodeBackground": "#FFFFFF80",
    "diffEditor.move.border": "#00308760",
    "diffEditor.moveActive.border": "#003087",
    "multiDiffEditor.headerBackground": "#F5F5F5",
    "multiDiffEditor.background": "#FFFFFF",
    "multiDiffEditor.border": "#7A650020",
    "editorInlayHint.background": "#F5F5F5",
    "editorInlayHint.foreground": "#44444470",
    "editorInlayHint.typeBackground": "#F5F5F5",
    "editorInlayHint.typeForeground": "#0A0C18",
    "editorInlayHint.parameterBackground": "#F5F5F5",
    "editorInlayHint.parameterForeground": "#44444470",
    "inlineChat.background": "#F5F5F5",
    "inlineChat.foreground": "#0A0C18",
    "inlineChat.border": "#00308730",
    "inlineChat.shadow": "#0A0C1820",
    "inlineChatInput.background": "#FFFFFF",
    "inlineChatInput.border": "#00308750",
    "inlineChatInput.focusBorder": "#003087",
    "inlineChatInput.placeholderForeground": "#44444470",
    "inlineChatDiff.inserted": "#339D3720",
    "inlineChatDiff.removed": "#E2233915",
    "chat.requestBorder": "#00308730",
    "chat.requestBackground": "#F5F5F5",
    "chat.slashCommandBackground": "#003087",
    "chat.slashCommandForeground": "#FFFFFF",
    "chat.avatarBackground": "#003087",
    "chat.avatarForeground": "#FFFFFF",
    "chat.editedFileForeground": "#003087",
    "chat.linesAddedForeground": "#339D37CC",
    "chat.linesRemovedForeground": "#E22339CC",
    "chat.requestCodeBorder": "#00308720",
    "chat.requestBubbleBackground": "#F5F5F5E6",
    "chat.requestBubbleHoverBackground": "#E0E0E0E6",
    "chat.checkpointSeparator": "#00308730",
    "chat.thinkingShimmer": "#00308730",
    "chatManagement.sashBorder": "#003087",
    "interactive.activeCodeBorder": "#003087",
    "interactive.inactiveCodeBorder": "#00308720",
    "gitDecoration.addedResourceForeground": "#339D37",
    "gitDecoration.modifiedResourceForeground": "#003087",
    "gitDecoration.deletedResourceForeground": "#E22339",
    "gitDecoration.renamedResourceForeground": "#003087",
    "gitDecoration.stageModifiedResourceForeground": "#003087CC",
    "gitDecoration.stageDeletedResourceForeground": "#E22339CC",
    "gitDecoration.untrackedResourceForeground": "#339D37",
    "gitDecoration.ignoredResourceForeground": "#78797E",
    "gitDecoration.conflictingResourceForeground": "#B38800",
    "gitDecoration.submoduleResourceForeground": "#006A8F",
    "git.blame.editorDecorationForeground": "#78797E80",
    "scmGraph.foreground1": "#003087",
    "scmGraph.foreground2": "#7A6500",
    "scmGraph.foreground3": "#0A690D",
    "scmGraph.foreground4": "#B38800",
    "scmGraph.foreground5": "#339D37",
    "scmGraph.historyItemHoverLabelForeground": "#0A0C18",
    "scmGraph.historyItemHoverAdditionsForeground": "#339D37",
    "scmGraph.historyItemHoverDeletionsForeground": "#E22339",
    "scmGraph.historyItemRefColor": "#003087",
    "scmGraph.historyItemRemoteRefColor": "#7A6500",
    "scmGraph.historyItemBaseRefColor": "#0A690D",
    "pickerGroup.border": "#00308720",
    "pickerGroup.foreground": "#003087",
    "quickInput.background": "#FFFFFF",
    "quickInput.foreground": "#0A0C18",
    "quickInputList.focusBackground": "#00308730",
    "quickInputList.focusForeground": "#0A0C18",
    "quickInputList.focusIconForeground": "#0A0C18",
    "quickInputTitle.background": "#F5F5F5",
    "keybindingLabel.background": "#00308715",
    "keybindingLabel.foreground": "#0A0C18",
    "keybindingLabel.border": "#00308730",
    "keybindingLabel.bottomBorder": "#00308750",
    "keybindingTable.headerBackground": "#F5F5F5",
    "keybindingTable.rowsBackground": "#F5F5F580",
    "testing.runAction": "#339D37",
    "testing.iconErrored": "#E22339",
    "testing.iconFailed": "#E22339",
    "testing.iconPassed": "#339D37",
    "testing.iconQueued": "#B38800",
    "testing.iconUnset": "#78797E",
    "testing.iconSkipped": "#78797E",
    "testing.iconErrored.retired": "#E2233950",
    "testing.iconFailed.retired": "#E2233950",
    "testing.iconPassed.retired": "#339D3750",
    "testing.iconQueued.retired": "#B3880050",
    "testing.iconUnset.retired": "#78797E50",
    "testing.iconSkipped.retired": "#78797E50",
    "testing.peekBorder": "#E22339",
    "testing.peekHeaderBackground": "#E2233915",
    "testing.message.error.lineBackground": "#E2233910",
    "testing.message.info.decorationForeground": "#5B9BD5",
    "testing.message.info.lineBackground": "#5B9BD510",
    "testing.messagePeekBorder": "#5B9BD5",
    "testing.messagePeekHeaderBackground": "#5B9BD515",
    "testing.coveredBackground": "#339D3710",
    "testing.coveredBorder": "#339D3730",
    "testing.coveredGutterBackground": "#339D3740",
    "testing.uncoveredBranchBackground": "#E2233920",
    "testing.uncoveredBackground": "#E2233910",
    "testing.uncoveredBorder": "#E2233930",
    "testing.uncoveredGutterBackground": "#E2233940",
    "testing.coverCountBadgeBackground": "#003087",
    "testing.coverCountBadgeForeground": "#FFFFFF",
    "testing.message.error.badgeBackground": "#E22339",
    "testing.message.error.badgeBorder": "#E2233960",
    "testing.message.error.badgeForeground": "#FFFFFF",
    "debugToolBar.background": "#FFFFFF",
    "debugView.exceptionLabelForeground": "#FFFFFF",
    "debugView.exceptionLabelBackground": "#E22339",
    "debugView.stateLabelForeground": "#FFFFFF",
    "debugView.stateLabelBackground": "#003087",
    "debugView.valueChangedHighlight": "#00308760",
    "debugTokenExpression.name": "#7A6500",
    "debugTokenExpression.value": "#0A690D",
    "debugTokenExpression.string": "#0A690D",
    "debugTokenExpression.boolean": "#006A8F",
    "debugTokenExpression.number": "#006A8F",
    "debugTokenExpression.error": "#E22339",
    "debugTokenExpression.type": "#7A6500",
    "debugIcon.breakpointForeground": "#E22339",
    "debugIcon.breakpointDisabledForeground": "#78797E",
    "debugIcon.breakpointUnverifiedForeground": "#B38800",
    "debugIcon.breakpointCurrentStackframeForeground": "#B38800",
    "debugIcon.breakpointStackframeForeground": "#339D37",
    "debugIcon.startForeground": "#339D37",
    "debugIcon.pauseForeground": "#B38800",
    "debugIcon.stopForeground": "#E22339",
    "debugIcon.disconnectForeground": "#E22339",
    "debugIcon.restartForeground": "#339D37",
    "debugIcon.stepOverForeground": "#003087",
    "debugIcon.stepIntoForeground": "#003087",
    "debugIcon.stepOutForeground": "#003087",
    "debugIcon.continueForeground": "#339D37",
    "debugIcon.stepBackForeground": "#003087",
    "debugConsole.infoForeground": "#5B9BD5",
    "debugConsole.warningForeground": "#B38800",
    "debugConsole.errorForeground": "#E22339",
    "debugConsole.sourceForeground": "#78797E",
    "debugConsoleInputIcon.foreground": "#003087",
    "notebook.editorBackground": "#FFFFFF",
    "notebook.cellBorderColor": "#7A650020",
    "notebook.cellHoverBackground": "#E0E0E0",
    "notebook.cellInsertionIndicator": "#003087",
    "notebook.cellStatusBarItemHoverBackground": "#00308720",
    "notebook.cellToolbarSeparator": "#7A650015",
    "notebook.cellEditorBackground": "#FFFFFF",
    "notebook.focusedCellBackground": "#F5F5F5",
    "notebook.focusedCellBorder": "#003087",
    "notebook.focusedEditorBorder": "#003087",
    "notebook.inactiveFocusedCellBorder": "#00308740",
    "notebook.inactiveSelectedCellBorder": "#00308720",
    "notebook.outputContainerBackgroundColor": "#F5F5F5",
    "notebook.outputContainerBorderColor": "#7A650015",
    "notebook.selectedCellBackground": "#00308715",
    "notebook.selectedCellBorder": "#00308760",
    "notebook.symbolHighlightBackground": "#00308720",
    "notebookScrollbarSlider.activeBackground": "#00308770",
    "notebookScrollbarSlider.background": "#00308730",
    "notebookScrollbarSlider.hoverBackground": "#00308750",
    "notebookStatusErrorIcon.foreground": "#E22339",
    "notebookStatusRunningIcon.foreground": "#003087",
    "notebookStatusSuccessIcon.foreground": "#339D37",
    "notebookEditorOverviewRuler.runningCellForeground": "#003087",
    "simpleFindWidget.sashBorder": "#003087",
    "gauge.background": "#FFFFFF",
    "gauge.foreground": "#0A0C18",
    "gauge.border": "#00308720",
    "gauge.warningBackground": "#B3880020",
    "gauge.warningForeground": "#B38800",
    "gauge.errorBackground": "#E2233920",
    "gauge.errorForeground": "#E22339",
    "welcomePage.background": "#FFFFFF",
    "welcomePage.progress.background": "#F5F5F5",
    "welcomePage.progress.foreground": "#003087",
    "welcomePage.tileBackground": "#F5F5F5",
    "welcomePage.tileHoverBackground": "#E0E0E0",
    "welcomePage.tileBorder": "#7A650015",
    "walkThrough.embeddedEditorBackground": "#F5F5F5",
    "walkthrough.stepTitle.foreground": "#0A0C18",
    "settings.headerForeground": "#0A0C18",
    "settings.modifiedItemIndicator": "#003087",
    "settings.dropdownBackground": "#FFFFFF",
    "settings.dropdownForeground": "#0A0C18",
    "settings.dropdownBorder": "#00308750",
    "settings.dropdownListBorder": "#00308720",
    "settings.checkboxBackground": "#FFFFFF",
    "settings.checkboxForeground": "#003087",
    "settings.checkboxBorder": "#00308750",
    "settings.rowHoverBackground": "#00308710",
    "settings.textInputBackground": "#FFFFFF",
    "settings.textInputForeground": "#0A0C18",
    "settings.textInputBorder": "#00308750",
    "settings.numberInputBackground": "#FFFFFF",
    "settings.numberInputForeground": "#0A0C18",
    "settings.numberInputBorder": "#00308750",
    "settings.focusedRowBackground": "#00308710",
    "settings.focusedRowBorder": "#00308730",
    "settings.headerBorder": "#7A650015",
    "settings.sashBorder": "#003087",
    "settings.settingsHeaderHoverForeground": "#003087",
    "breadcrumb.foreground": "#78797E",
    "breadcrumb.background": "#FFFFFF",
    "breadcrumb.focusForeground": "#0A0C18",
    "breadcrumb.activeSelectionForeground": "#003087",
    "breadcrumbPicker.background": "#FFFFFF",
    "symbolIcon.arrayForeground": "#006A8F",
    "symbolIcon.booleanForeground": "#006A8F",
    "symbolIcon.classForeground": "#7A6500",
    "symbolIcon.colorForeground": "#003087",
    "symbolIcon.constantForeground": "#006A8F",
    "symbolIcon.constructorForeground": "#003087",
    "symbolIcon.enumeratorForeground": "#7A6500",
    "symbolIcon.enumeratorMemberForeground": "#006A8F",
    "symbolIcon.eventForeground": "#B38800",
    "symbolIcon.fieldForeground": "#003087",
    "symbolIcon.fileForeground": "#78797E",
    "symbolIcon.folderForeground": "#003087",
    "symbolIcon.functionForeground": "#003087",
    "symbolIcon.interfaceForeground": "#7A6500",
    "symbolIcon.keyForeground": "#003087",
    "symbolIcon.keywordForeground": "#7A6500",
    "symbolIcon.methodForeground": "#003087",
    "symbolIcon.moduleForeground": "#003087",
    "symbolIcon.namespaceForeground": "#003087",
    "symbolIcon.nullForeground": "#78797E",
    "symbolIcon.numberForeground": "#006A8F",
    "symbolIcon.objectForeground": "#003087",
    "symbolIcon.operatorForeground": "#003087",
    "symbolIcon.packageForeground": "#003087",
    "symbolIcon.propertyForeground": "#0A0C18",
    "symbolIcon.referenceForeground": "#003087",
    "symbolIcon.snippetForeground": "#0A690D",
    "symbolIcon.stringForeground": "#0A690D",
    "symbolIcon.structForeground": "#7A6500",
    "symbolIcon.textForeground": "#0A0C18",
    "symbolIcon.typeParameterForeground": "#7A6500",
    "symbolIcon.unitForeground": "#006A8F",
    "symbolIcon.variableForeground": "#0A0C18",
    "extensionButton.prominentForeground": "#FFFFFF",
    "extensionButton.prominentBackground": "#003087",
    "extensionButton.prominentHoverBackground": "#00206B",
    "extensionButton.background": "#003087",
    "extensionButton.foreground": "#FFFFFF",
    "extensionButton.hoverBackground": "#00206B",
    "extensionButton.separator": "#FFFFFF40",
    "extensionBadge.remoteBackground": "#003087",
    "extensionBadge.remoteForeground": "#FFFFFF",
    "extensionIcon.starForeground": "#B38800",
    "extensionIcon.verifiedForeground": "#339D37",
    "extensionIcon.preReleaseForeground": "#003087",
    "extensionIcon.sponsorForeground": "#7A6500",
    "extensionIcon.privateForeground": "#78797E",
    "extensionButton.border": "#00308700",
    "mcpIcon.starForeground": "#B38800",
    "charts.foreground": "#0A0C18",
    "charts.lines": "#78797E",
    "charts.red": "#E22339",
    "charts.blue": "#003087",
    "charts.yellow": "#B38800",
    "charts.orange": "#006A8F",
    "charts.green": "#339D37",
    "charts.purple": "#7A6500",
    "markdownAlert.note.foreground": "#5B9BD5",
    "markdownAlert.tip.foreground": "#339D37",
    "markdownAlert.important.foreground": "#7A6500",
    "markdownAlert.warning.foreground": "#B38800",
    "markdownAlert.caution.foreground": "#E22339",
    "agentSessionReadIndicator.foreground": "#003087",
    "agentStatusIndicator.background": "#003087",
    "actionBar.toggledBackground": "#00308730",
    "ports.iconRunningProcessForeground": "#339D37",
    "commentsView.resolvedIcon": "#339D37",
    "commentsView.unresolvedIcon": "#B38800"
  },
  "tokenColors": [
    {
      "name": "Comment",
      "scope": [
        "comment",
        "punctuation.definition.comment"
      ],
      "settings": {
        "fontStyle": "italic",
        "foreground": "#6E6F74"
      }
    },
    {
      "name": "Variables",
      "scope": [
        "variable",
        "string constant.other.placeholder"
      ],
      "settings": {
        "foreground": "#0A0C18"
      }
    },
    {
      "name": "Colors",
      "scope": [
        "constant.other.color"
      ],
      "settings": {
        "foreground": "#003087"
      }
    },
    {
      "name": "Invalid",
      "scope": [
        "invalid",
        "invalid.illegal"
      ],
      "settings": {
        "foreground": "#E22339"
      }
    },
    {
      "name": "Keyword, Storage",
      "scope": [
        "keyword",
        "storage.type",
        "storage.modifier"
      ],
      "settings": {
        "foreground": "#7A6500"
      }
    },
    {
      "name": "Operator, Misc",
      "scope": [
        "keyword.control",
        "constant.other.color",
        "punctuation",
        "meta.tag",
        "punctuation.definition.tag",
        "punctuation.separator.inheritance.php",
        "punctuation.definition.tag.html",
        "punctuation.definition.tag.begin.html",
        "punctuation.definition.tag.end.html",
        "punctuation.section.embedded",
        "keyword.other.template",
        "keyword.other.substitution"
      ],
      "settings": {
        "foreground": "#003087"
      }
    },
    {
      "name": "Tag",
      "scope": [
        "entity.name.tag",
        "meta.tag.sgml",
        "markup.deleted.git_gutter"
      ],
      "settings": {
        "foreground": "#7A6500"
      }
    },
    {
      "name": "Function, Special Method",
      "scope": [
        "entity.name.function",
        "meta.function-call",
        "variable.function",
        "support.function",
        "keyword.other.special-method"
      ],
      "settings": {
        "foreground": "#003087"
      }
    },
    {
      "name": "Block Level Variables",
      "scope": [
        "meta.block variable.other"
      ],
      "settings": {
        "foreground": "#0A0C18"
      }
    },
    {
      "name": "Other Variable, String Link",
      "scope": [
        "support.other.variable",
        "string.other.link"
      ],
      "settings": {
        "foreground": "#0A0C18"
      }
    },
    {
      "name": "Number, Constant, Function Argument, Tag Attribute, Embedded",
      "scope": [
        "constant.numeric",
        "constant.language",
        "support.constant",
        "constant.character",
        "constant.escape",
        "variable.parameter",
        "keyword.other.unit",
        "keyword.other"
      ],
      "settings": {
        "foreground": "#006A8F"
      }
    },
    {
      "name": "String, Symbols, Inherited Class, Markup Heading",
      "scope": [
        "string",
        "constant.other.symbol",
        "constant.other.key",
        "entity.other.inherited-class",
        "markup.heading",
        "markup.inserted.git_gutter",
        "meta.group.braces.curly constant.other.object.key.js string.unquoted.label.js"
      ],
      "settings": {
        "foreground": "#0A690D"
      }
    },
    {
      "name": "Class, Support",
      "scope": [
        "entity.name",
        "support.type",
        "support.class",
        "support.other.namespace.use.php",
        "meta.use.php",
        "support.other.namespace.php",
        "markup.changed.git_gutter",
        "support.type.sys-types"
      ],
      "settings": {
        "foreground": "#003087"
      }
    },
    {
      "name": "Entity Types",
      "scope": [
        "support.type"
      ],
      "settings": {
        "foreground": "#7A6500"
      }
    },
    {
      "name": "CSS Class and Support",
      "scope": [
        "source.css support.type.property-name",
        "source.sass support.type.property-name",
        "source.scss support.type.property-name",
        "source.less support.type.property-name",
        "source.stylus support.type.property-name",
        "source.postcss support.type.property-name"
      ],
      "settings": {
        "foreground": "#003087"
      }
    },
    {
      "name": "Sub-methods",
      "scope": [
        "entity.name.module.js",
        "variable.import.parameter.js",
        "variable.other.class.js"
      ],
      "settings": {
        "foreground": "#0A0C18"
      }
    },
    {
      "name": "Language methods",
      "scope": [
        "variable.language"
      ],
      "settings": {
        "fontStyle": "italic",
        "foreground": "#7A6500"
      }
    },
    {
      "name": "entity.name.method.js",
      "scope": [
        "entity.name.method.js"
      ],
      "settings": {
        "fontStyle": "italic",
        "foreground": "#003087"
      }
    },
    {
      "name": "meta.method.js",
      "scope": [
        "meta.class-method.js entity.name.function.js",
        "variable.function.constructor"
      ],
      "settings": {
        "foreground": "#003087"
      }
    },
    {
      "name": "Attributes",
      "scope": [
        "entity.other.attribute-name"
      ],
      "settings": {
        "foreground": "#7A6500"
      }
    },
    {
      "name": "HTML Attributes",
      "scope": [
        "text.html.basic entity.other.attribute-name.html",
        "text.html.basic entity.other.attribute-name"
      ],
      "settings": {
        "fontStyle": "italic",
        "foreground": "#003087"
      }
    },
    {
      "name": "CSS Classes",
      "scope": [
        "entity.other.attribute-name.class"
      ],
      "settings": {
        "foreground": "#003087"
      }
    },
    {
      "name": "CSS ID's",
      "scope": [
        "source.sass keyword.control"
      ],
      "settings": {
        "foreground": "#003087"
      }
    },
    {
      "name": "Inserted",
      "scope": [
        "markup.inserted"
      ],
      "settings": {
        "foreground": "#339D37"
      }
    },
    {
      "name": "Deleted",
      "scope": [
        "markup.deleted"
      ],
      "settings": {
        "foreground": "#E22339"
      }
    },
    {
      "name": "Changed",
      "scope": [
        "markup.changed"
      ],
      "settings": {
        "foreground": "#003087"
      }
    },
    {
      "name": "Regular Expressions",
      "scope": [
        "string.regexp"
      ],
      "settings": {
        "foreground": "#0A690D"
      }
    },
    {
      "name": "Escape Characters",
      "scope": [
        "constant.character.escape"
      ],
      "settings": {
        "foreground": "#0A690D"
      }
    },
    {
      "name": "URL",
      "scope": [
        "*url*",
        "*link*",
        "*uri*"
      ],
      "settings": {
        "fontStyle": "underline"
      }
    },
    {
      "name": "Decorators",
      "scope": [
        "tag.decorator.js entity.name.tag.js",
        "tag.decorator.js punctuation.definition.tag.js"
      ],
      "settings": {
        "fontStyle": "italic",
        "foreground": "#003087"
      }
    },
    {
      "name": "ES7 Bind Operator",
      "scope": [
        "source.js constant.other.object.key.js string.unquoted.label.js"
      ],
      "settings": {
        "fontStyle": "italic",
        "foreground": "#0A0C18"
      }
    },
    {
      "name": "JSON Key - Level 0",
      "scope": [
        "source.json meta.structure.dictionary.json support.type.property-name.json"
      ],
      "settings": {
        "foreground": "#003087"
      }
    },
    {
      "name": "JSON Key - Level 1",
      "scope": [
        "source.json meta.structure.dictionary.json meta.structure.dictionary.value.json meta.structure.dictionary.json support.type.property-name.json"
      ],
      "settings": {
        "foreground": "#7A6500"
      }
    },
    {
      "name": "JSON Key - Level 2",
      "scope": [
        "source.json meta.structure.dictionary.json meta.structure.dictionary.value.json meta.structure.dictionary.json meta.structure.dictionary.value.json meta.structure.dictionary.json support.type.property-name.json"
      ],
      "settings": {
        "foreground": "#0A690D"
      }
    },
    {
      "name": "JSON Key - Level 3",
      "scope": [
        "source.json meta.structure.dictionary.json meta.structure.dictionary.value.json meta.structure.dictionary.json meta.structure.dictionary.value.json meta.structure.dictionary.json meta.structure.dictionary.value.json meta.structure.dictionary.json support.type.property-name.json"
      ],
      "settings": {
        "foreground": "#006A8F"
      }
    },
    {
      "name": "Markdown - Plain",
      "scope": [
        "text.html.markdown",
        "punctuation.definition.list_item.markdown"
      ],
      "settings": {
        "foreground": "#0A0C18"
      }
    },
    {
      "name": "Markdown - Markup Raw Inline",
      "scope": [
        "text.html.markdown markup.inline.raw.markdown"
      ],
      "settings": {
        "foreground": "#7A6500"
      }
    },
    {
      "name": "Markdown - Markup Raw Inline Punctuation",
      "scope": [
        "text.html.markdown markup.inline.raw.markdown punctuation.definition.raw.markdown"
      ],
      "settings": {
        "foreground": "#003087"
      }
    },
    {
      "name": "Markdown - Heading",
      "scope": [
        "markdown.heading",
        "markup.heading | markup.heading entity.name",
        "markup.heading.markdown punctuation.definition.heading.markdown"
      ],
      "settings": {
        "foreground": "#003087"
      }
    },
    {
      "name": "Markup - Italic",
      "scope": [
        "markup.italic"
      ],
      "settings": {
        "fontStyle": "italic",
        "foreground": "#7A6500"
      }
    },
    {
      "name": "Markup - Bold",
      "scope": [
        "markup.bold",
        "markup.bold string"
      ],
      "settings": {
        "fontStyle": "bold",
        "foreground": "#7A6500"
      }
    },
    {
      "name": "Markup - Bold-Italic",
      "scope": [
        "markup.bold markup.italic",
        "markup.italic markup.bold",
        "markup.quote markup.bold",
        "markup.bold markup.italic string",
        "markup.italic markup.bold string",
        "markup.quote markup.bold string"
      ],
      "settings": {
        "fontStyle": "bold",
        "foreground": "#7A6500"
      }
    },
    {
      "name": "Markup - Underline",
      "scope": [
        "markup.underline"
      ],
      "settings": {
        "fontStyle": "underline",
        "foreground": "#0A690D"
      }
    },
    {
      "name": "Markdown - Blockquote",
      "scope": [
        "markup.quote punctuation.definition.blockquote.markdown"
      ],
      "settings": {
        "foreground": "#5B9BD5"
      }
    },
    {
      "name": "Markup - Quote",
      "scope": [
        "markup.quote"
      ],
      "settings": {
        "fontStyle": "italic"
      }
    },
    {
      "name": "Markdown - Link",
      "scope": [
        "string.other.link.title.markdown"
      ],
      "settings": {
        "foreground": "#003087"
      }
    },
    {
      "name": "Markdown - Link Description",
      "scope": [
        "string.other.link.description.title.markdown"
      ],
      "settings": {
        "foreground": "#7A6500"
      }
    },
    {
      "name": "Markdown - Link Anchor",
      "scope": [
        "constant.other.reference.link.markdown"
      ],
      "settings": {
        "foreground": "#0A690D"
      }
    },
    {
      "name": "Markup - Raw Block",
      "scope": [
        "markup.raw.block"
      ],
      "settings": {
        "foreground": "#7A6500"
      }
    },
    {
      "name": "Markdown - Raw Block Fenced",
      "scope": [
        "markup.raw.block.fenced.markdown"
      ],
      "settings": {
        "foreground": "#0A0C18"
      }
    },
    {
      "name": "Markdown - Fenced Code Block",
      "scope": [
        "punctuation.definition.fenced.markdown"
      ],
      "settings": {
        "foreground": "#0A0C18"
      }
    },
    {
      "name": "Markdown - Fenced Code Block Variable",
      "scope": [
        "markup.raw.block.fenced.markdown",
        "variable.language.fenced.markdown",
        "punctuation.section.class.end"
      ],
      "settings": {
        "foreground": "#0A0C18"
      }
    },
    {
      "name": "Markdown - Fenced Language",
      "scope": [
        "variable.language.fenced.markdown"
      ],
      "settings": {
        "foreground": "#003087"
      }
    },
    {
      "name": "Markdown - Separator",
      "scope": [
        "meta.separator"
      ],
      "settings": {
        "fontStyle": "bold",
        "foreground": "#003087"
      }
    },
    {
      "name": "Markup - Table",
      "scope": [
        "markup.table"
      ],
      "settings": {
        "foreground": "#0A0C18"
      }
    }
  ],
  "semanticHighlighting": true,
  "semanticTokenColors": {
    "enumMember": "#006A8F",
    "variable.constant": "#006A8F",
    "variable.defaultLibrary": "#7A6500",
    "variable.readonly": "#0A0C18",
    "property.readonly": "#006A8F",
    "parameter": "#0A0C18",
    "type": {
      "foreground": "#7A6500",
      "italic": true
    },
    "interface": {
      "foreground": "#7A6500",
      "italic": true
    },
    "enum": "#7A6500",
    "namespace": "#003087",
    "decorator": "#7A6500",
    "variable:dart": "#0A0C18",
    "property:dart": "#003087",
    "annotation:dart": "#7A6500",
    "parameter.label:dart": "#0A0C18"
  },
  "name": "ACT Light",
  "displayName": "ACT Light",
  "description": "A professional theme for Visual Studio Code featuring the Australian Capital Territory's iconic blue and gold colour palette.",
  "version": "1.0.0",
  "publisher": "lucidlabs"
}
